nonebot_plugin_everyday_en/__init__.py
nonebot_plugin_everyday_en/config.py
nonebot_plugin_everyday_en-1.1.5.dist-info/LICENSE
nonebot_plugin_everyday_en-1.1.5.dist-info/WHEEL
nonebot_plugin_everyday_en-1.1.5.dist-info/METADATA
nonebot_plugin_everyday_en-1.1.5.dist-info/RECORD
