Metadata-Version: 2.1
Name: nonebot-plugin-everyday-en
Version: 1.1.5
Summary: 每日一句英文句子。完整帮助文档，可选搭配软依赖nonebot_plugin_apscheduler实现定时发送
Home-page: https://github.com/MelodyYuuka/nonebot_plugin_everyday_en
License: MIT
Author: MelodyYuuka
Requires-Python: >=3.7
Classifier: License :: OSI Approved :: MIT License
Classifier: Programming Language :: Python :: 3
Classifier: Programming Language :: Python :: 3.10
Classifier: Programming Language :: Python :: 3.7
Classifier: Programming Language :: Python :: 3.8
Classifier: Programming Language :: Python :: 3.9
Requires-Dist: aiofiles (>=0.7.0)
Requires-Dist: httpx (>=0.19.0)
Requires-Dist: nonebot-adapter-onebot (>=2.0.0-beta.1)
Requires-Dist: nonebot2 (>=2.0.0-beta.1)
Project-URL: Repository, https://github.com/MelodyYuuka/nonebot_plugin_everyday_en
